{"tenant_id": "tenant_data_v2/company_1", "primary_user": {"user_id": "alice", "full_name": "Alice Anastasiou", "email": "alice@company.com"}, "users": [{"user_id": "alice", "full_name": "Alice Anastasiou", "email": "alice@company.com"}, {"user_id": "eden", "full_name": "Eden Berhe", "email": "eden@company.com"}, {"user_id": "oubunmi", "full_name": "Oubunmi Gboyega", "email": "oubunmi@company.com"}, {"user_id": "juan", "full_name": "Juan Quispe", "email": "juan@company.com"}, {"user_id": "gorosti", "full_name": "Gorosti Egiagarai", "email": "gorosti@company.com"}, {"user_id": "bhushan", "full_name": "Bhushan Magar", "email": "bhushan@company.com"}, {"user_id": "valarie", "full_name": "Valarie Cabral", "email": "valarie@company.com"}, {"user_id": "cassie", "full_name": "Cassie Hicks", "email": "cassie@company.com"}], "user_id_to_documents": {"alice": [{"url": "company_1/works on", "title": "works on", "content": "[{\"employee ssn\": 123456789, \"project number\": 1, \"hours\": 32.5}, {\"employee ssn\": 123456789, \"project number\": 2, \"hours\": 7.5}, {\"employee ssn\": 666884444, \"project number\": 3, \"hours\": 40.0}, {\"employee ssn\": 453453453, \"project number\": 1, \"hours\": 20.0}, {\"employee ssn\": 453453453, \"project number\": 2, \"hours\": 20.0}, {\"employee ssn\": 333445555, \"project number\": 2, \"hours\": 10.0}, {\"employee ssn\": 333445555, \"project number\": 3, \"hours\": 10.0}, {\"employee ssn\": 333445555, \"project number\": 10, \"hours\": 10.0}, {\"employee ssn\": 333445555, \"project number\": 20, \"hours\": 10.0}, {\"employee ssn\": 999887777, \"project number\": 30, \"hours\": 30.0}, {\"employee ssn\": 999887777, \"project number\": 10, \"hours\": 10.0}, {\"employee ssn\": 987987987, \"project number\": 10, \"hours\": 35.0}, {\"employee ssn\": 987987987, \"project number\": 30, \"hours\": 5.0}, {\"employee ssn\": 987654321, \"project number\": 30, \"hours\": 20.0}, {\"employee ssn\": 987654321, \"project number\": 20, \"hours\": 15.0}, {\"employee ssn\": 888665555, \"project number\": 20, \"hours\": null}]"}], "eden": [{"url": "company_1/employee_0", "title": "employee", "content": "[{\"first name\": \"Jonh\", \"minit\": \"B\", \"last name\": \"Smith\", \"ssn\": 123456789, \"birth date\": \"1965-01-09\", \"address\": \"731 Fondren, Houston, TX\", \"sex\": \"M\", \"salary\": 30000, \"super ssn\": 333445555, \"department no\": 5}, {\"first name\": \"Franklin\", \"minit\": \"T\", \"last name\": \"Wong\", \"ssn\": 333445555, \"birth date\": \"1955-12-08\", \"address\": \"638 Voss, Houston, TX\", \"sex\": \"M\", \"salary\": 40000, \"super ssn\": 888665555, \"department no\": 5}, {\"first name\": \"Joyce\", \"minit\": \"A\", \"last name\": \"English\", \"ssn\": 453453453, \"birth date\": \"1972-07-31\", \"address\": \"5631 Rice, Houston, TX\", \"sex\": \"F\", \"salary\": 25000, \"super ssn\": 333445555, \"department no\": 5}, {\"first name\": \"Ramesh\", \"minit\": \"K\", \"last name\": \"Narayan\", \"ssn\": 666884444, \"birth date\": \"1962-09-15\", \"address\": \"975 Fire Oak, Humble, TX\", \"sex\": \"M\", \"salary\": 38000, \"super ssn\": 333445555, \"department no\": 5}]"}], "oubunmi": [{"url": "company_1/employee_1", "title": "employee", "content": "[{\"first name\": \"James\", \"minit\": \"E\", \"last name\": \"Borg\", \"ssn\": 888665555, \"birth date\": \"1937-11-10\", \"address\": \"450 Stone, Houston, TX\", \"sex\": \"M\", \"salary\": 55000, \"super ssn\": null, \"department no\": 1}, {\"first name\": \"Jennifier\", \"minit\": \"S\", \"last name\": \"Wallace\", \"ssn\": 987654321, \"birth date\": \"1941-06-20\", \"address\": \"291 Berry, Bellaire, TX\", \"sex\": \"F\", \"salary\": 43000, \"super ssn\": 888665555, \"department no\": 4}, {\"first name\": \"Ahmad\", \"minit\": \"V\", \"last name\": \"Jabbar\", \"ssn\": 987987987, \"birth date\": \"1969-03-29\", \"address\": \"980 Dallas, Houston, TX\", \"sex\": \"M\", \"salary\": 25000, \"super ssn\": 987654321, \"department no\": 4}, {\"first name\": \"Alicia\", \"minit\": \"J\", \"last name\": \"Zelaya\", \"ssn\": 999887777, \"birth date\": \"1968-01-19\", \"address\": \"3321 Castle, Spring, TX\", \"sex\": \"F\", \"salary\": 25000, \"super ssn\": 987654321, \"department no\": 4}]"}], "juan": [{"url": "company_1/department", "title": "department", "content": "[{\"department name\": \"Headquarters\", \"department number\": 1, \"manager ssn\": 888665555, \"manager start date\": \"1981-06-19\"}, {\"department name\": \"Administration\", \"department number\": 4, \"manager ssn\": 987654321, \"manager start date\": \"1995-01-01\"}, {\"department name\": \"Research\", \"department number\": 5, \"manager ssn\": 333445555, \"manager start date\": \"1988-05-22\"}]"}], "gorosti": [], "bhushan": [{"url": "company_1/dependent", "title": "dependent", "content": "[{\"employee ssn\": 333445555, \"dependent name\": \"Alice\", \"sex\": \"F\", \"birth date\": \"1986-04-05\", \"relationship\": \"Daughter\"}, {\"employee ssn\": 333445555, \"dependent name\": \"Theodore\", \"sex\": \"M\", \"birth date\": \"1983-10-25\", \"relationship\": \"Son\"}, {\"employee ssn\": 333445555, \"dependent name\": \"Joy\", \"sex\": \"F\", \"birth date\": \"1958-05-03\", \"relationship\": \"Spouse\"}, {\"employee ssn\": 987654321, \"dependent name\": \"Abner\", \"sex\": \"M\", \"birth date\": \"1942-02-28\", \"relationship\": \"Spouse\"}, {\"employee ssn\": 123456789, \"dependent name\": \"Michael\", \"sex\": \"M\", \"birth date\": \"1988-01-04\", \"relationship\": \"Son\"}, {\"employee ssn\": 123456789, \"dependent name\": \"Alice\", \"sex\": \"F\", \"birth date\": \"1988-12-30\", \"relationship\": \"Daughter\"}, {\"employee ssn\": 123456789, \"dependent name\": \"Elizabeth\", \"sex\": \"F\", \"birth date\": \"1967-05-05\", \"relationship\": \"Spouse\"}]"}], "valarie": [{"url": "company_1/department locations", "title": "department locations", "content": "[{\"department number\": 1, \"department location\": \"Houston\"}, {\"department number\": 4, \"department location\": \"Stafford\"}, {\"department number\": 5, \"department location\": \"Bellaire\"}, {\"department number\": 5, \"department location\": \"Sugarland\"}, {\"department number\": 5, \"department location\": \"Houston\"}]"}], "cassie": [{"url": "General knowledge/cassie", "title": "Try contacting Juan Quispe", "content": "juan has relevant information on following topics: department"}]}, "user_id_to_descriptions": {"alice": " The user might have information about employees and their project numbers and hours worked.", "eden": " The user might have information about employees, including their personal details, demographics, and employment-related information.", "oubunmi": " The user might have information about employees, including their personal details, demographics, and employment-related information.", "bhushan": " The user might have information about dependents, including their personal details, demographics, and relationship with the employee.", "valarie": " The user might have information about department locations, including department numbers and locations.", "cassie": " The user might have information about departments, including the department name, number, manager, and manager's start date."}, "user_id_to_table_names": {"alice": ["works on"], "eden": ["employee"], "oubunmi": ["employee"], "juan": ["department"], "gorosti": [], "bhushan": ["dependent"], "valarie": ["department locations"], "cassie": []}, "user_id_to_descriptions_templated": {"alice": "User might have information about `works on` topic with respect to following attributes: ['employee ssn', 'project number', 'hours']", "eden": "User might have information about `employee` topic with respect to following attributes: ['first name', 'minit', 'last name', 'ssn', 'birth date', 'address', 'sex', 'salary', 'super ssn', 'department no']", "oubunmi": "User might have information about `employee` topic with respect to following attributes: ['first name', 'minit', 'last name', 'ssn', 'birth date', 'address', 'sex', 'salary', 'super ssn', 'department no']", "bhushan": "User might have information about `dependent` topic with respect to following attributes: ['employee ssn', 'dependent name', 'sex', 'birth date', 'relationship']", "valarie": "User might have information about `department locations` topic with respect to following attributes: ['department number', 'department location']", "cassie": "User might have information about `department` topic with respect to following attributes: ['department name', 'department number', 'manager ssn', 'manager start date']"}, "user_id_to_descriptions_lowprecision": {}, "user_id_to_descriptions_lowprecision_templated": {}}