{"tenant_id": "tenant_data_v2/network_1", "primary_user": {"user_id": "alice", "full_name": "Alice Anastasiou", "email": "alice@company.com"}, "users": [{"user_id": "alice", "full_name": "Alice Anastasiou", "email": "alice@company.com"}, {"user_id": "parker", "full_name": "Parker McLean", "email": "parker@company.com"}, {"user_id": "farshid", "full_name": "Farshid Kamangar", "email": "farshid@company.com"}], "user_id_to_documents": {"alice": [{"url": "network_1/high schooler", "title": "high schooler", "content": "[{\"id\": 1510, \"name\": \"Jordan\", \"grade\": 9}, {\"id\": 1689, \"name\": \"Gabriel\", \"grade\": 9}, {\"id\": 1381, \"name\": \"Tiffany\", \"grade\": 9}, {\"id\": 1709, \"name\": \"Cassandra\", \"grade\": 9}, {\"id\": 1101, \"name\": \"Haley\", \"grade\": 10}, {\"id\": 1782, \"name\": \"Andrew\", \"grade\": 10}, {\"id\": 1468, \"name\": \"Kris\", \"grade\": 10}, {\"id\": 1641, \"name\": \"Brittany\", \"grade\": 10}, {\"id\": 1247, \"name\": \"Alexis\", \"grade\": 11}, {\"id\": 1316, \"name\": \"Austin\", \"grade\": 11}, {\"id\": 1911, \"name\": \"Gabriel\", \"grade\": 11}, {\"id\": 1501, \"name\": \"Jessica\", \"grade\": 11}, {\"id\": 1304, \"name\": \"Jordan\", \"grade\": 12}, {\"id\": 1025, \"name\": \"John\", \"grade\": 12}, {\"id\": 1934, \"name\": \"Kyle\", \"grade\": 12}, {\"id\": 1661, \"name\": \"Logan\", \"grade\": 12}]"}], "parker": [{"url": "network_1/friend", "title": "friend", "content": "[{\"student id\": 1510, \"friend id\": 1381}, {\"student id\": 1510, \"friend id\": 1689}, {\"student id\": 1689, \"friend id\": 1709}, {\"student id\": 1381, \"friend id\": 1247}, {\"student id\": 1709, \"friend id\": 1247}, {\"student id\": 1689, \"friend id\": 1782}, {\"student id\": 1782, \"friend id\": 1468}, {\"student id\": 1782, \"friend id\": 1316}, {\"student id\": 1782, \"friend id\": 1304}, {\"student id\": 1468, \"friend id\": 1101}, {\"student id\": 1468, \"friend id\": 1641}, {\"student id\": 1101, \"friend id\": 1641}, {\"student id\": 1247, \"friend id\": 1911}, {\"student id\": 1247, \"friend id\": 1501}, {\"student id\": 1911, \"friend id\": 1501}, {\"student id\": 1501, \"friend id\": 1934}, {\"student id\": 1316, \"friend id\": 1934}, {\"student id\": 1934, \"friend id\": 1304}, {\"student id\": 1304, \"friend id\": 1661}, {\"student id\": 1661, \"friend id\": 1025}]"}], "farshid": [{"url": "network_1/likes", "title": "likes", "content": "[{\"student id\": 1689, \"liked id\": 1709}, {\"student id\": 1709, \"liked id\": 1689}, {\"student id\": 1782, \"liked id\": 1709}, {\"student id\": 1911, \"liked id\": 1247}, {\"student id\": 1247, \"liked id\": 1468}, {\"student id\": 1641, \"liked id\": 1468}, {\"student id\": 1316, \"liked id\": 1304}, {\"student id\": 1501, \"liked id\": 1934}, {\"student id\": 1934, \"liked id\": 1501}, {\"student id\": 1025, \"liked id\": 1101}]"}]}, "user_id_to_descriptions": {"alice": " The user might have information about high schoolers, including their names and grades.", "parker": " User might have information about students and their friend ids.", "farshid": " User might have information about students and their liked ids."}, "user_id_to_table_names": {"alice": ["high schooler"], "parker": ["friend"], "farshid": ["likes"]}, "user_id_to_descriptions_templated": {"alice": "User might have information about `high schooler` topic with respect to following attributes: ['id', 'name', 'grade']", "parker": "User might have information about `friend` topic with respect to following attributes: ['student id', 'friend id']", "farshid": "User might have information about `likes` topic with respect to following attributes: ['student id', 'liked id']"}, "user_id_to_descriptions_lowprecision": {}, "user_id_to_descriptions_lowprecision_templated": {}}