{"tenant_id": "tenant_data_v2/school_bus", "primary_user": {"user_id": "alice", "full_name": "Alice Anastasiou", "email": "alice@company.com"}, "users": [{"user_id": "alice", "full_name": "Alice Anastasiou", "email": "alice@company.com"}, {"user_id": "lina", "full_name": "Lina Wagner", "email": "lina@company.com"}, {"user_id": "parker", "full_name": "Parker McLean", "email": "parker@company.com"}, {"user_id": "bhushan", "full_name": "Bhushan Magar", "email": "bhushan@company.com"}], "user_id_to_documents": {"alice": [{"url": "school_bus/driver", "title": "driver", "content": "[{\"driver id\": 1, \"name\": \"Matthew Ritter\", \"party\": \"Dem\", \"home city\": \"Hartford\", \"age\": 40}, {\"driver id\": 2, \"name\": \"Dan Carter\", \"party\": \"Rep\", \"home city\": \"Bethel\", \"age\": 30}, {\"driver id\": 3, \"name\": \"Minnie Gonzalez\", \"party\": \"Dem\", \"home city\": \"Hartford\", \"age\": 46}, {\"driver id\": 4, \"name\": \"Angel Acre\", \"party\": \"Dem\", \"home city\": \"Hartford\", \"age\": 42}, {\"driver id\": 5, \"name\": \"Brandon McGee\", \"party\": \"Dem\", \"home city\": \"Hartford\", \"age\": 45}, {\"driver id\": 6, \"name\": \"Edwin Vargas\", \"party\": \"Dem\", \"home city\": \"Hartford\", \"age\": 52}, {\"driver id\": 7, \"name\": \"Douglas McCrory\", \"party\": \"Dem\", \"home city\": \"Hartford\", \"age\": 36}, {\"driver id\": 8, \"name\": \"Timothy Ackert\", \"party\": \"Rep\", \"home city\": \"Coventry\", \"age\": 35}, {\"driver id\": 9, \"name\": \"Jason Rojas\", \"party\": \"Dem\", \"home city\": \"East Hartford\", \"age\": 38}, {\"driver id\": 10, \"name\": \"Henry Genga\", \"party\": \"Dem\", \"home city\": \"East Hartford\", \"age\": 37}, {\"driver id\": 11, \"name\": \"Tim Larson\", \"party\": \"Dem\", \"home city\": \"East Hartford\", \"age\": 36}, {\"driver id\": 12, \"name\": \"Geoff Luxenberg\", \"party\": \"Dem\", \"home city\": \"Manchester\", \"age\": 52}]"}], "lina": [{"url": "school_bus/school", "title": "school", "content": "[{\"school id\": 1, \"grade\": \"Kindergarten\", \"school\": \"Noelani Elementary School\", \"location\": \"Honolulu, Hawaii\", \"type\": \"Public\"}, {\"school id\": 2, \"grade\": \"1st-3rd grade\", \"school\": \"St. Francis Assisi\", \"location\": \"Jakarta, Indonesia\", \"type\": \"Private Catholic\"}, {\"school id\": 3, \"grade\": \"4th grade\", \"school\": \"State Elementary School Menteng 01\", \"location\": \"Jakarta, Indonesia\", \"type\": \"Public\"}, {\"school id\": 4, \"grade\": \"5th-12th grade\", \"school\": \"Punahou School\", \"location\": \"Honolulu, Hawaii\", \"type\": \"Private\"}, {\"school id\": 5, \"grade\": \"Freshman\\u2013Sophomore year\", \"school\": \"Occidental College\", \"location\": \"Los Angeles, California\", \"type\": \"Private\"}, {\"school id\": 6, \"grade\": \"Junior\\u2013Senior year\", \"school\": \"Columbia University\", \"location\": \"New York City\", \"type\": \"Private\"}, {\"school id\": 7, \"grade\": \"College\", \"school\": \"Harvard Law School\", \"location\": \"Cambridge, Massachusetts\", \"type\": \"Private\"}]"}], "parker": [{"url": "school_bus/school bus", "title": "school bus", "content": "[{\"school id\": 1, \"driver id\": 10, \"years working\": 10, \"if full time\": \"F\"}, {\"school id\": 5, \"driver id\": 7, \"years working\": 8, \"if full time\": \"T\"}, {\"school id\": 3, \"driver id\": 4, \"years working\": 6, \"if full time\": \"T\"}, {\"school id\": 7, \"driver id\": 9, \"years working\": 2, \"if full time\": \"T\"}, {\"school id\": 4, \"driver id\": 3, \"years working\": 3, \"if full time\": \"T\"}]"}], "bhushan": [{"url": "General knowledge/bhushan", "title": "Try contacting Parker McLean", "content": "parker has relevant information on following topics: school bus"}]}, "user_id_to_descriptions": {"alice": " The user might have information about drivers, including their personal details, party affiliation, home city, and age.", "lina": " The user might have information about schools, including their grades, locations, and types.", "bhushan": " The user might have information about school buses, including the school id, driver id, years working, and whether the driver is full time."}, "user_id_to_table_names": {"alice": ["driver"], "lina": ["school"], "parker": ["school bus"], "bhushan": []}, "user_id_to_descriptions_templated": {"alice": "User might have information about `driver` topic with respect to following attributes: ['driver id', 'name', 'party', 'home city', 'age']", "lina": "User might have information about `school` topic with respect to following attributes: ['school id', 'grade', 'school', 'location', 'type']", "bhushan": "User might have information about `school bus` topic with respect to following attributes: ['school id', 'driver id', 'years working', 'if full time']"}, "user_id_to_descriptions_lowprecision": {}, "user_id_to_descriptions_lowprecision_templated": {}}