{"tenant_id": "tenant_data_v2/storm_record", "primary_user": {"user_id": "alice", "full_name": "Alice Anastasiou", "email": "alice@company.com"}, "users": [{"user_id": "alice", "full_name": "Alice Anastasiou", "email": "alice@company.com"}, {"user_id": "niks", "full_name": "Niks Dzenis", "email": "niks@company.com"}, {"user_id": "tulga", "full_name": "Tulga Bat-Erdene", "email": "tulga@company.com"}], "user_id_to_documents": {"alice": [{"url": "storm_record/storm", "title": "storm", "content": "[{\"storm id\": 1, \"name\": \"One\", \"dates active\": \"May19\\u2013May25\", \"max speed\": 995, \"damage millions usd\": 13.0, \"number deaths\": 0}, {\"storm id\": 2, \"name\": \"Two\", \"dates active\": \"August3\\u2013August10\", \"max speed\": 972, \"damage millions usd\": 10.75, \"number deaths\": 7}, {\"storm id\": 3, \"name\": \"Three\", \"dates active\": \"August5\\u2013August14\", \"max speed\": 972, \"damage millions usd\": 13.0, \"number deaths\": 52}, {\"storm id\": 4, \"name\": \"Four\", \"dates active\": \"August26\\u2013September2\", \"max speed\": 961, \"damage millions usd\": 4.05, \"number deaths\": 7}, {\"storm id\": 5, \"name\": \"Five\", \"dates active\": \"September7\\u2013September17\", \"max speed\": 988, \"damage millions usd\": 1.49, \"number deaths\": 3}, {\"storm id\": 6, \"name\": \"Six\", \"dates active\": \"September18\\u2013September25\", \"max speed\": 1002, \"damage millions usd\": 0.039, \"number deaths\": 2}, {\"storm id\": 7, \"name\": \"Seven\", \"dates active\": \"September22\\u2013September28\", \"max speed\": 977, \"damage millions usd\": 13.0, \"number deaths\": 0}, {\"storm id\": 8, \"name\": \"Eight\", \"dates active\": \"October20\\u2013October24\", \"max speed\": 983, \"damage millions usd\": 13.0, \"number deaths\": 0}, {\"storm id\": 9, \"name\": \"Nine\", \"dates active\": \"October24\\u2013October26\", \"max speed\": 1007, \"damage millions usd\": 13.0, \"number deaths\": 0}, {\"storm id\": 10, \"name\": \"9 cyclones\", \"dates active\": \"May19 \\u2013October26\", \"max speed\": 961, \"damage millions usd\": 29.3, \"number deaths\": 71}]"}], "niks": [{"url": "storm_record/region", "title": "region", "content": "[{\"region id\": 1, \"region code\": \"AF\", \"region name\": \"Afghanistan\"}, {\"region id\": 2, \"region code\": \"AL\", \"region name\": \"Albania\"}, {\"region id\": 3, \"region code\": \"DZ\", \"region name\": \"Algeria\"}, {\"region id\": 4, \"region code\": \"DS\", \"region name\": \"American Samoa\"}, {\"region id\": 5, \"region code\": \"AD\", \"region name\": \"Andorra\"}, {\"region id\": 6, \"region code\": \"AO\", \"region name\": \"Angola\"}, {\"region id\": 7, \"region code\": \"AI\", \"region name\": \"Anguilla\"}, {\"region id\": 8, \"region code\": \"AQ\", \"region name\": \"Antarctica\"}, {\"region id\": 9, \"region code\": \"AG\", \"region name\": \"Antigua and Barbuda\"}, {\"region id\": 10, \"region code\": \"CY\", \"region name\": \"Cyprus\"}, {\"region id\": 11, \"region code\": \"CZ\", \"region name\": \"Czech Republic\"}, {\"region id\": 12, \"region code\": \"DK\", \"region name\": \"Denmark\"}, {\"region id\": 13, \"region code\": \"DJ\", \"region name\": \"Djibouti\"}]"}], "tulga": [{"url": "storm_record/affected region", "title": "affected region", "content": "[{\"region id\": 1, \"storm id\": 1, \"number city affected\": 10.0}, {\"region id\": 2, \"storm id\": 1, \"number city affected\": 15.0}, {\"region id\": 3, \"storm id\": 3, \"number city affected\": 30.0}, {\"region id\": 1, \"storm id\": 4, \"number city affected\": 22.0}, {\"region id\": 12, \"storm id\": 5, \"number city affected\": 37.0}, {\"region id\": 2, \"storm id\": 5, \"number city affected\": 12.0}]"}]}, "user_id_to_descriptions": {"alice": " The user might have information about storms, including their names, active dates, maximum speeds, damage costs, and number of deaths.", "niks": " The user might have information about regions, including their ids, codes, and names.", "tulga": " The user might have information about affected regions, including the region id, storm id, and the number of cities affected."}, "user_id_to_table_names": {"alice": ["storm"], "niks": ["region"], "tulga": ["affected region"]}, "user_id_to_descriptions_templated": {"alice": "User might have information about `storm` topic with respect to following attributes: ['storm id', 'name', 'dates active', 'max speed', 'damage millions usd', 'number deaths']", "niks": "User might have information about `region` topic with respect to following attributes: ['region id', 'region code', 'region name']", "tulga": "User might have information about `affected region` topic with respect to following attributes: ['region id', 'storm id', 'number city affected']"}, "user_id_to_descriptions_lowprecision": {}, "user_id_to_descriptions_lowprecision_templated": {}}